{
  "generatedAt": "2026-04-05T17:35:16.979Z",
  "count": 11,
  "sources": [
    {
      "id": "ct-policing-prevent-programme",
      "provider": "Counter Terrorism Policing - Prevent",
      "endpoint": "https://www.counterterrorism.police.uk/what-we-do/counter-terrorism/prevent/",
      "kind": "html",
      "lane": "prevention",
      "region": "uk",
      "status": "auto-quarantined",
      "reason": "Repeated blocked-or-auth failures on html source",
      "quarantinedAt": "2026-04-05T17:35:16.979Z",
      "lastErrorCategory": "blocked-or-auth",
      "lastErrorMessage": "Blocked by anti-bot protection",
      "consecutiveBlockedFailures": 2,
      "lastFailureAt": "2026-04-05T17:35:16.979Z",
      "lastCheckedAt": "2026-04-05T17:35:16.979Z"
    },
    {
      "id": "ct-policing-what-you-can-do",
      "provider": "Counter Terrorism Policing - What You Can Do",
      "endpoint": "https://www.counterterrorism.police.uk/what-you-can-do/",
      "kind": "html",
      "lane": "prevention",
      "region": "uk",
      "status": "auto-quarantined",
      "reason": "Repeated blocked-or-auth failures on html source",
      "quarantinedAt": "2026-04-05T17:35:16.979Z",
      "lastErrorCategory": "blocked-or-auth",
      "lastErrorMessage": "Blocked by anti-bot protection",
      "consecutiveBlockedFailures": 2,
      "lastFailureAt": "2026-04-05T17:35:16.979Z",
      "lastCheckedAt": "2026-04-05T17:35:16.979Z"
    },
    {
      "id": "mi5-terrorism-threat-levels",
      "provider": "MI5 - Terrorism Threat Levels",
      "endpoint": "https://www.mi5.gov.uk/threats-and-advice/terrorism-threat-levels",
      "kind": "html",
      "lane": "prevention",
      "region": "uk",
      "status": "auto-quarantined",
      "reason": "Repeated blocked-or-auth failures on html source",
      "quarantinedAt": "2026-04-05T17:35:16.979Z",
      "lastErrorCategory": "blocked-or-auth",
      "lastErrorMessage": "HTTP 403",
      "consecutiveBlockedFailures": 2,
      "lastFailureAt": "2026-04-05T17:35:16.979Z",
      "lastCheckedAt": "2026-04-05T17:35:16.979Z"
    },
    {
      "id": "npsa-blog-news",
      "provider": "NPSA - Blog News",
      "endpoint": "https://www.npsa.gov.uk/blog/news",
      "kind": "html",
      "lane": "prevention",
      "region": "uk",
      "status": "auto-quarantined",
      "reason": "Repeated blocked-or-auth failures on html source",
      "quarantinedAt": "2026-04-05T17:35:16.979Z",
      "lastErrorCategory": "blocked-or-auth",
      "lastErrorMessage": "HTTP 403",
      "consecutiveBlockedFailures": 2,
      "lastFailureAt": "2026-04-05T17:35:16.979Z",
      "lastCheckedAt": "2026-04-05T17:35:16.979Z"
    },
    {
      "id": "uk-ncsc-homepage",
      "provider": "UK NCSC - Homepage",
      "endpoint": "https://www.ncsc.gov.uk/",
      "kind": "html",
      "lane": "prevention",
      "region": "uk",
      "status": "auto-quarantined",
      "reason": "Repeated blocked-or-auth failures on html source",
      "quarantinedAt": "2026-04-05T17:35:16.979Z",
      "lastErrorCategory": "blocked-or-auth",
      "lastErrorMessage": "Blocked by anti-bot protection",
      "consecutiveBlockedFailures": 2,
      "lastFailureAt": "2026-04-05T17:35:16.979Z",
      "lastCheckedAt": "2026-04-05T17:35:16.979Z"
    },
    {
      "id": "hope-not-hate-home",
      "provider": "Hope Not Hate",
      "endpoint": "https://www.hopenothate.org.uk/",
      "kind": "html",
      "lane": "context",
      "region": "uk",
      "status": "auto-quarantined",
      "reason": "Repeated blocked-or-auth failures on html source",
      "quarantinedAt": "2026-04-05T16:42:53.076Z",
      "lastErrorCategory": "blocked-or-auth",
      "lastErrorMessage": "HTTP 403",
      "consecutiveBlockedFailures": 2,
      "lastFailureAt": "2026-04-05T16:42:53.076Z",
      "lastCheckedAt": "2026-04-05T16:42:53.076Z"
    },
    {
      "id": "police-scotland-news",
      "provider": "Police Scotland a News",
      "endpoint": "https://www.scotland.police.uk/whats-happening/news/",
      "kind": "html",
      "lane": "incidents",
      "region": "uk",
      "status": "auto-quarantined",
      "reason": "Repeated blocked-or-auth failures on html source",
      "quarantinedAt": "2026-04-05T15:36:10.273Z",
      "lastErrorCategory": "blocked-or-auth",
      "lastErrorMessage": "HTTP 403",
      "consecutiveBlockedFailures": 2,
      "lastFailureAt": "2026-04-05T15:36:10.273Z",
      "lastCheckedAt": "2026-04-05T15:36:10.273Z"
    },
    {
      "id": "police-scotland-whats-happening-news",
      "provider": "Police Scotland - What's Happening News",
      "endpoint": "https://www.scotland.police.uk/what-s-happening/news/",
      "kind": "html",
      "lane": "incidents",
      "region": "uk",
      "status": "auto-quarantined",
      "reason": "Repeated blocked-or-auth failures on html source",
      "quarantinedAt": "2026-04-05T15:36:10.273Z",
      "lastErrorCategory": "blocked-or-auth",
      "lastErrorMessage": "HTTP 403",
      "consecutiveBlockedFailures": 2,
      "lastFailureAt": "2026-04-05T15:36:10.273Z",
      "lastCheckedAt": "2026-04-05T15:36:10.273Z"
    },
    {
      "id": "gchq-counter-terrorism",
      "provider": "GCHQ a Counter-Terrorism",
      "endpoint": "https://www.gchq.gov.uk/section/mission/counter-terrorism",
      "kind": "html",
      "lane": "prevention",
      "region": "uk",
      "status": "auto-quarantined",
      "reason": "Repeated blocked-or-auth failures on html source",
      "quarantinedAt": "2026-04-05T13:02:51.966Z",
      "lastErrorCategory": "blocked-or-auth",
      "lastErrorMessage": "Blocked by anti-bot protection",
      "consecutiveBlockedFailures": 2,
      "lastFailureAt": "2026-04-05T13:02:51.966Z",
      "lastCheckedAt": "2026-04-05T13:02:51.966Z"
    },
    {
      "id": "npsa-national-protective-security-authority",
      "provider": "National Protective Security Authority (NPSA) a Updates",
      "endpoint": "https://www.npsa.gov.uk/news",
      "kind": "html",
      "lane": "prevention",
      "region": "uk",
      "status": "auto-quarantined",
      "reason": "Repeated blocked-or-auth failures on html source",
      "quarantinedAt": "2026-04-05T13:02:51.966Z",
      "lastErrorCategory": "blocked-or-auth",
      "lastErrorMessage": "HTTP 403",
      "consecutiveBlockedFailures": 2,
      "lastFailureAt": "2026-04-05T13:02:51.966Z",
      "lastCheckedAt": "2026-04-05T13:02:51.966Z"
    },
    {
      "id": "london-resilience",
      "provider": "London Resilience a Updates",
      "endpoint": "https://www.london.gov.uk/about-us/organisations-we-work/london-resilience",
      "kind": "html",
      "lane": "prevention",
      "region": "london",
      "status": "catalog-quarantined",
      "reason": "Marked quarantined in sources catalog",
      "quarantinedAt": "",
      "lastErrorCategory": "",
      "lastErrorMessage": "",
      "consecutiveBlockedFailures": 0,
      "lastFailureAt": "",
      "lastCheckedAt": ""
    }
  ]
}
