{
  "generatedFrom": "live-alerts.json",
  "generatedAt": "2026-04-26T08:16:04.847Z",
  "totalSourceErrors": 89,
  "top20": [
    {
      "id": "germany-federal-prosecutor-current-press-en",
      "provider": "German Federal Public Prosecutor - Current Press Releases (EN)",
      "endpoint": "https://www.generalbundesanwalt.de/EN/Press/current_press_releases/current_press_releases_node.html",
      "finalUrl": "",
      "category": "not-found-404",
      "statusKind": "",
      "message": "HTTP 404",
      "status": 404,
      "rankScore": 5,
      "suggestedAction": "move source to quarantine and replace endpoint with current live URL",
      "replacementCandidate": "",
      "sourceKind": "html",
      "sourceLane": "context",
      "sourceRegion": "",
      "isMachineReadable": false
    },
    {
      "id": "hedayah-news",
      "provider": "Hedayah - News",
      "endpoint": "https://hedayah.com/news/",
      "finalUrl": "",
      "category": "not-found-404",
      "statusKind": "",
      "message": "HTTP 404",
      "status": 404,
      "rankScore": 5,
      "suggestedAction": "move source to quarantine and replace endpoint with current live URL",
      "replacementCandidate": "",
      "sourceKind": "html",
      "sourceLane": "prevention",
      "sourceRegion": "",
      "isMachineReadable": false
    },
    {
      "id": "austria-interior-ministry-news",
      "provider": "Austrian Interior Ministry - News",
      "endpoint": "https://www.bmi.gv.at/news.aspx",
      "finalUrl": "https://www.bmi.gv.at/myracloud-blocked/?r=YzQ5NTQ3. ZjY0MTE5NWNmODAzMTMx. Mm. UyOWMwZGJm. Zjg1MDFjMTI1. Nm. Zj. Zjdm. YzY3&t=ODg3N2. YwY2. Nm. Mjg3NTg5. MjI2L0. Fwci8yMDI2. Oj. Ew. Oj. Ez. OjM3ICsw. Mj. Aw&w=ODkxZTUwODhiNDA0N2U2. ZjdkOGZm. Nm. ZlMDZiNTQw. ZmM4OWM1ZGQ5ZDRl. NjA2. Mzc4",
      "category": "moved-temporarily",
      "statusKind": "",
      "message": "HTTP 503",
      "status": 503,
      "rankScore": 4,
      "suggestedAction": "update source endpoint to redirected final URL",
      "replacementCandidate": "https://www.bmi.gv.at/myracloud-blocked/?r=YzQ5NTQ3. ZjY0MTE5NWNmODAzMTMx. Mm. UyOWMwZGJm. Zjg1MDFjMTI1. Nm. Zj. Zjdm. YzY3&t=ODg3N2. YwY2. Nm. Mjg3NTg5. MjI2L0. Fwci8yMDI2. Oj. Ew. Oj. Ez. OjM3ICsw. Mj. Aw&w=ODkxZTUwODhiNDA0N2U2. ZjdkOGZm. Nm. ZlMDZiNTQw. ZmM4OWM1ZGQ5ZDRl. NjA2. Mzc4",
      "sourceKind": "html",
      "sourceLane": "context",
      "sourceRegion": "",
      "isMachineReadable": false
    },
    {
      "id": "chatham-house-home",
      "provider": "Chatham House",
      "endpoint": "https://www.chathamhouse.org",
      "finalUrl": "https://www.chathamhouse.org/",
      "category": "moved-temporarily",
      "statusKind": "",
      "message": "HTTP 403",
      "status": 403,
      "rankScore": 4,
      "suggestedAction": "update source endpoint to redirected final URL",
      "replacementCandidate": "https://www.chathamhouse.org/",
      "sourceKind": "html",
      "sourceLane": "context",
      "sourceRegion": "",
      "isMachineReadable": false
    },
    {
      "id": "daily-mail-online",
      "provider": "Daily Mail Online - Popular Stories",
      "endpoint": "https://www.dailymail.co.uk/home/index.rss",
      "finalUrl": "https://www.dailymail.com/home/index.rss",
      "category": "moved-temporarily",
      "statusKind": "",
      "message": "Blocked by anti-bot protection",
      "status": 200,
      "rankScore": 4,
      "suggestedAction": "update source endpoint to redirected final URL",
      "replacementCandidate": "https://www.dailymail.com/home/index.rss",
      "sourceKind": "rss",
      "sourceLane": "context",
      "sourceRegion": "",
      "isMachineReadable": true
    },
    {
      "id": "ec-planv-crimen-organizado",
      "provider": "Plan V - Crimen Organizado",
      "endpoint": "https://planv.com.ec/historias/crimen-organizado/",
      "finalUrl": "https://planv.com.ec/historias/planverde/crimen-organizado-delincuencia-comun-e-invasores-asechan-areas-protegidas/",
      "category": "moved-temporarily",
      "statusKind": "",
      "message": "Blocked by anti-bot protection",
      "status": 200,
      "rankScore": 4,
      "suggestedAction": "update source endpoint to redirected final URL",
      "replacementCandidate": "https://planv.com.ec/historias/planverde/crimen-organizado-delincuencia-comun-e-invasores-asechan-areas-protegidas/",
      "sourceKind": "html",
      "sourceLane": "context",
      "sourceRegion": "",
      "isMachineReadable": false
    },
    {
      "id": "ec-primicias-seguridad",
      "provider": "Primicias - Seguridad",
      "endpoint": "https://www.primicias.ec/seguridad",
      "finalUrl": "https://www.primicias.ec/seguridad/",
      "category": "moved-temporarily",
      "statusKind": "",
      "message": "Blocked by anti-bot protection",
      "status": 200,
      "rankScore": 4,
      "suggestedAction": "update source endpoint to redirected final URL",
      "replacementCandidate": "https://www.primicias.ec/seguridad/",
      "sourceKind": "html",
      "sourceLane": "context",
      "sourceRegion": "",
      "isMachineReadable": false
    },
    {
      "id": "echr-uk-grand-chamber-rss",
      "provider": "European Court of Human Rights - HUDOC",
      "endpoint": "https://hudoc.echr.coe.int/",
      "finalUrl": "https://hudoc.echr.coe.int/#{%22documentcollectionid2%22:[%22GRANDCHAMBER%22,%22CHAMBER%22]}",
      "category": "moved-temporarily",
      "statusKind": "",
      "message": "Blocked by anti-bot protection",
      "status": 0,
      "rankScore": 4,
      "suggestedAction": "update source endpoint to redirected final URL",
      "replacementCandidate": "https://hudoc.echr.coe.int/#{%22documentcollectionid2%22:[%22GRANDCHAMBER%22,%22CHAMBER%22]}",
      "sourceKind": "html",
      "sourceLane": "oversight",
      "sourceRegion": "",
      "isMachineReadable": false
    },
    {
      "id": "netherlands-om-terrorisme",
      "provider": "Dutch Public Prosecution Service - Terrorisme",
      "endpoint": "https://www.om.nl/onderwerpen/terrorisme",
      "finalUrl": "https://www.om.nl/onderwerpen/t/terrorisme",
      "category": "moved-temporarily",
      "statusKind": "",
      "message": "Blocked by anti-bot protection",
      "status": 200,
      "rankScore": 4,
      "suggestedAction": "update source endpoint to redirected final URL",
      "replacementCandidate": "https://www.om.nl/onderwerpen/t/terrorisme",
      "sourceKind": "html",
      "sourceLane": "context",
      "sourceRegion": "",
      "isMachineReadable": false
    },
    {
      "id": "netherlands-om-terrorismefinanciering-nieuws",
      "provider": "Dutch Public Prosecution Service - Terrorismefinanciering Nieuws",
      "endpoint": "https://www.om.nl/onderwerpen/terrorismefinanciering/nieuws",
      "finalUrl": "https://www.om.nl/onderwerpen/t/terrorismefinanciering/nieuws",
      "category": "moved-temporarily",
      "statusKind": "",
      "message": "HTTP 404",
      "status": 404,
      "rankScore": 4,
      "suggestedAction": "update source endpoint to redirected final URL",
      "replacementCandidate": "https://www.om.nl/onderwerpen/t/terrorismefinanciering/nieuws",
      "sourceKind": "html",
      "sourceLane": "context",
      "sourceRegion": "",
      "isMachineReadable": false
    },
    {
      "id": "occrp-news",
      "provider": "OCCRP a Organized Crime and Corruption Reporting Project",
      "endpoint": "https://www.occrp.org/en/news",
      "finalUrl": "https://www.occrp.org/en/news/page/1",
      "category": "moved-temporarily",
      "statusKind": "",
      "message": "Blocked by anti-bot protection",
      "status": 200,
      "rankScore": 4,
      "suggestedAction": "update source endpoint to redirected final URL",
      "replacementCandidate": "https://www.occrp.org/en/news/page/1",
      "sourceKind": "html",
      "sourceLane": "context",
      "sourceRegion": "",
      "isMachineReadable": false
    },
    {
      "id": "politico-europe",
      "provider": "Politico Europe",
      "endpoint": "https://www.politico.eu",
      "finalUrl": "https://www.politico.eu/",
      "category": "moved-temporarily",
      "statusKind": "",
      "message": "Blocked by anti-bot protection",
      "status": 200,
      "rankScore": 4,
      "suggestedAction": "update source endpoint to redirected final URL",
      "replacementCandidate": "https://www.politico.eu/",
      "sourceKind": "html",
      "sourceLane": "context",
      "sourceRegion": "",
      "isMachineReadable": false
    },
    {
      "id": "soufan-center-intelbrief",
      "provider": "The Soufan Center a Intel. Brief",
      "endpoint": "https://thesoufancenter.org/intelbrief",
      "finalUrl": "https://thesoufancenter.org/intelbrief/",
      "category": "moved-temporarily",
      "statusKind": "",
      "message": "Blocked by anti-bot protection",
      "status": 200,
      "rankScore": 4,
      "suggestedAction": "update source endpoint to redirected final URL",
      "replacementCandidate": "https://thesoufancenter.org/intelbrief/",
      "sourceKind": "html",
      "sourceLane": "context",
      "sourceRegion": "",
      "isMachineReadable": false
    },
    {
      "id": "acled-updates",
      "provider": "ACLED a Updates and Analysis",
      "endpoint": "https://acleddata.com/updates",
      "finalUrl": "",
      "category": "anti-bot-protection",
      "statusKind": "",
      "message": "Blocked by anti-bot protection",
      "status": 200,
      "rankScore": 2,
      "suggestedAction": "downgrade to non-bot-protected endpoint or quarantine if no public feed",
      "replacementCandidate": "",
      "sourceKind": "html",
      "sourceLane": "context",
      "sourceRegion": "",
      "isMachineReadable": false
    },
    {
      "id": "barking-dagenham-council-news",
      "provider": "Barking and Dagenham Council a News",
      "endpoint": "https://www.lbbd.gov.uk/news",
      "finalUrl": "",
      "category": "blocked-or-auth",
      "statusKind": "",
      "message": "HTTP 403",
      "status": 403,
      "rankScore": 2,
      "suggestedAction": "downgrade to non-bot-protected endpoint or quarantine if no public feed",
      "replacementCandidate": "",
      "sourceKind": "html",
      "sourceLane": "context",
      "sourceRegion": "",
      "isMachineReadable": false
    },
    {
      "id": "barnet-council-news",
      "provider": "Barnet Post",
      "endpoint": "https://barnetpost.co.uk/",
      "finalUrl": "",
      "category": "anti-bot-protection",
      "statusKind": "",
      "message": "Blocked by anti-bot protection",
      "status": 200,
      "rankScore": 2,
      "suggestedAction": "downgrade to non-bot-protected endpoint or quarantine if no public feed",
      "replacementCandidate": "",
      "sourceKind": "html",
      "sourceLane": "context",
      "sourceRegion": "",
      "isMachineReadable": false
    },
    {
      "id": "bromley-council-news",
      "provider": "Bromley Council a Newsroom",
      "endpoint": "https://www.bromley.gov.uk/news",
      "finalUrl": "",
      "category": "anti-bot-protection",
      "statusKind": "",
      "message": "Blocked by anti-bot protection",
      "status": 200,
      "rankScore": 2,
      "suggestedAction": "downgrade to non-bot-protected endpoint or quarantine if no public feed",
      "replacementCandidate": "",
      "sourceKind": "html",
      "sourceLane": "context",
      "sourceRegion": "",
      "isMachineReadable": false
    },
    {
      "id": "counter-extremism-project-news",
      "provider": "Counter Extremism Project a News",
      "endpoint": "https://www.counterextremism.com/news-and-media",
      "finalUrl": "",
      "category": "anti-bot-protection",
      "statusKind": "",
      "message": "Blocked by anti-bot protection",
      "status": 200,
      "rankScore": 2,
      "suggestedAction": "downgrade to non-bot-protected endpoint or quarantine if no public feed",
      "replacementCandidate": "",
      "sourceKind": "html",
      "sourceLane": "context",
      "sourceRegion": "",
      "isMachineReadable": false
    },
    {
      "id": "curia-press-rss-en",
      "provider": "Court of Justice of the European Union - RSS (EN/FR)",
      "endpoint": "https://curia.europa.eu/site/rss.jsp?lang=en&second. Lang=fr",
      "finalUrl": "",
      "category": "blocked-or-auth",
      "statusKind": "",
      "message": "HTTP 403",
      "status": 403,
      "rankScore": 2,
      "suggestedAction": "downgrade to non-bot-protected endpoint or quarantine if no public feed",
      "replacementCandidate": "",
      "sourceKind": "rss",
      "sourceLane": "oversight",
      "sourceRegion": "",
      "isMachineReadable": true
    },
    {
      "id": "de-cemas-digital-seismograph",
      "provider": "CeMAS - Digital Seismograph",
      "endpoint": "https://cemas.io/en/projects/digital-seismograph/",
      "finalUrl": "",
      "category": "anti-bot-protection",
      "statusKind": "",
      "message": "Blocked by anti-bot protection",
      "status": 200,
      "rankScore": 2,
      "suggestedAction": "downgrade to non-bot-protected endpoint or quarantine if no public feed",
      "replacementCandidate": "",
      "sourceKind": "html",
      "sourceLane": "prevention",
      "sourceRegion": "",
      "isMachineReadable": false
    }
  ]
}
