{
  "generatedFrom": "live-alerts.json",
  "generatedAt": "2026-04-14T23:12:39.349Z",
  "totalSourceErrors": 115,
  "top20": [
    {
      "id": "belgium-crisis-centre-news",
      "provider": "Belgian National Crisis Centre - News",
      "endpoint": "https://crisiscenter.be/en/news",
      "finalUrl": "",
      "category": "not-found-404",
      "statusKind": "",
      "message": "HTTP 404",
      "status": 404,
      "rankScore": 5,
      "suggestedAction": "move source to quarantine and replace endpoint with current live URL",
      "replacementCandidate": "",
      "sourceKind": "html",
      "sourceLane": "context",
      "sourceRegion": "",
      "isMachineReadable": false
    },
    {
      "id": "chatham-house-rss",
      "provider": "Chatham House a Research & Commentary (RSS)",
      "endpoint": "https://www.chathamhouse.org/publications.rss",
      "finalUrl": "",
      "category": "not-found-404",
      "statusKind": "",
      "message": "HTTP 404",
      "status": 404,
      "rankScore": 5,
      "suggestedAction": "move source to quarantine and replace endpoint with current live URL",
      "replacementCandidate": "",
      "sourceKind": "rss",
      "sourceLane": "context",
      "sourceRegion": "",
      "isMachineReadable": true
    },
    {
      "id": "dni-press-releases",
      "provider": "Office of the Director of National Intelligence - Press Releases",
      "endpoint": "https://www.dni.gov/index.php/newsroom/press-releases",
      "finalUrl": "",
      "category": "not-found-404",
      "statusKind": "",
      "message": "HTTP 404",
      "status": 404,
      "rankScore": 5,
      "suggestedAction": "move source to quarantine and replace endpoint with current live URL",
      "replacementCandidate": "",
      "sourceKind": "html",
      "sourceLane": "context",
      "sourceRegion": "",
      "isMachineReadable": false
    },
    {
      "id": "doj-nsd-press-releases",
      "provider": "U.S. Department of Justice - National Security Division Press Releases",
      "endpoint": "https://www.justice.gov/nsd/press-releases",
      "finalUrl": "",
      "category": "not-found-404",
      "statusKind": "",
      "message": "HTTP 404",
      "status": 404,
      "rankScore": 5,
      "suggestedAction": "move source to quarantine and replace endpoint with current live URL",
      "replacementCandidate": "",
      "sourceKind": "html",
      "sourceLane": "context",
      "sourceRegion": "",
      "isMachineReadable": false
    },
    {
      "id": "gctf-news",
      "provider": "Global Counterterrorism Forum (GCTF) a News",
      "endpoint": "https://www.thegctf.org/News/",
      "finalUrl": "",
      "category": "not-found-404",
      "statusKind": "",
      "message": "HTTP 404",
      "status": 404,
      "rankScore": 5,
      "suggestedAction": "move source to quarantine and replace endpoint with current live URL",
      "replacementCandidate": "",
      "sourceKind": "html",
      "sourceLane": "oversight",
      "sourceRegion": "",
      "isMachineReadable": false
    },
    {
      "id": "german-bfv-news",
      "provider": "German BfV - News",
      "endpoint": "https://www.verfassungsschutz.de/EN/service/news/news_node.html",
      "finalUrl": "",
      "category": "not-found-404",
      "statusKind": "",
      "message": "HTTP 404",
      "status": 404,
      "rankScore": 5,
      "suggestedAction": "move source to quarantine and replace endpoint with current live URL",
      "replacementCandidate": "",
      "sourceKind": "html",
      "sourceLane": "context",
      "sourceRegion": "",
      "isMachineReadable": false
    },
    {
      "id": "joint-committee-human-rights-html",
      "provider": "Joint Committee on Human Rights",
      "endpoint": "https://www.gov.uk/government/organisations/joint-committee-on-human-rights",
      "finalUrl": "",
      "category": "not-found-404",
      "statusKind": "",
      "message": "HTTP 404",
      "status": 404,
      "rankScore": 5,
      "suggestedAction": "move source to quarantine and replace endpoint with current live URL",
      "replacementCandidate": "",
      "sourceKind": "html",
      "sourceLane": "oversight",
      "sourceRegion": "",
      "isMachineReadable": false
    },
    {
      "id": "london-assembly-press-releases",
      "provider": "London Assembly a Press Releases",
      "endpoint": "https://www.london.gov.uk/media-centre/london-assembly-press-releases/rss.xml",
      "finalUrl": "",
      "category": "not-found-404",
      "statusKind": "",
      "message": "HTTP 404",
      "status": 404,
      "rankScore": 5,
      "suggestedAction": "move source to quarantine and replace endpoint with current live URL",
      "replacementCandidate": "",
      "sourceKind": "rss",
      "sourceLane": "oversight",
      "sourceRegion": "",
      "isMachineReadable": true
    },
    {
      "id": "mayor-of-london-press-releases",
      "provider": "Mayor of London a Press Releases",
      "endpoint": "https://www.london.gov.uk/media-centre/mayors-press-releases/rss.xml",
      "finalUrl": "",
      "category": "not-found-404",
      "statusKind": "",
      "message": "HTTP 404",
      "status": 404,
      "rankScore": 5,
      "suggestedAction": "move source to quarantine and replace endpoint with current live URL",
      "replacementCandidate": "",
      "sourceKind": "rss",
      "sourceLane": "context",
      "sourceRegion": "",
      "isMachineReadable": true
    },
    {
      "id": "mi5-news-rss-direct",
      "provider": "MI5 - News RSS",
      "endpoint": "https://www.mi5.gov.uk/news/rss.xml",
      "finalUrl": "",
      "category": "not-found-404",
      "statusKind": "",
      "message": "HTTP 404",
      "status": 404,
      "rankScore": 5,
      "suggestedAction": "move source to quarantine and replace endpoint with current live URL",
      "replacementCandidate": "",
      "sourceKind": "rss",
      "sourceLane": "context",
      "sourceRegion": "",
      "isMachineReadable": true
    },
    {
      "id": "nctv-nl-english",
      "provider": "NCTV (Netherlands) a English News",
      "endpoint": "https://english.nctv.nl/topics/terrorist-threat-assessment-netherlands",
      "finalUrl": "",
      "category": "not-found-404",
      "statusKind": "",
      "message": "HTTP 404",
      "status": 404,
      "rankScore": 5,
      "suggestedAction": "move source to quarantine and replace endpoint with current live URL",
      "replacementCandidate": "",
      "sourceKind": "html",
      "sourceLane": "prevention",
      "sourceRegion": "",
      "isMachineReadable": false
    },
    {
      "id": "pet-dk-english",
      "provider": "PET (Denmark) a English News",
      "endpoint": "https://pet.dk/en/news/",
      "finalUrl": "",
      "category": "not-found-404",
      "statusKind": "",
      "message": "HTTP 404",
      "status": 404,
      "rankScore": 5,
      "suggestedAction": "move source to quarantine and replace endpoint with current live URL",
      "replacementCandidate": "",
      "sourceKind": "html",
      "sourceLane": "prevention",
      "sourceRegion": "",
      "isMachineReadable": false
    },
    {
      "id": "rte-ireland-news-rss",
      "provider": "RTE News - Ireland (RSS)",
      "endpoint": "https://www.rte.ie/news/rss/news-ireland.xml",
      "finalUrl": "",
      "category": "not-found-404",
      "statusKind": "",
      "message": "HTTP 404",
      "status": 404,
      "rankScore": 5,
      "suggestedAction": "move source to quarantine and replace endpoint with current live URL",
      "replacementCandidate": "",
      "sourceKind": "rss",
      "sourceLane": "context",
      "sourceRegion": "",
      "isMachineReadable": true
    },
    {
      "id": "scottish-government-justice-news",
      "provider": "Scottish Government - Justice and Safety",
      "endpoint": "https://www.gov.scot/justice-and-law/",
      "finalUrl": "",
      "category": "not-found-404",
      "statusKind": "",
      "message": "HTTP 404",
      "status": 404,
      "rankScore": 5,
      "suggestedAction": "move source to quarantine and replace endpoint with current live URL",
      "replacementCandidate": "",
      "sourceKind": "html",
      "sourceLane": "oversight",
      "sourceRegion": "",
      "isMachineReadable": false
    },
    {
      "id": "slam-news",
      "provider": "South London and Maudsley NHS Foundation Trust a News",
      "endpoint": "https://slam.nhs.uk/news/",
      "finalUrl": "",
      "category": "not-found-404",
      "statusKind": "",
      "message": "HTTP 404",
      "status": 404,
      "rankScore": 5,
      "suggestedAction": "move source to quarantine and replace endpoint with current live URL",
      "replacementCandidate": "",
      "sourceKind": "html",
      "sourceLane": "context",
      "sourceRegion": "",
      "isMachineReadable": false
    },
    {
      "id": "unodc-news",
      "provider": "UNODC (UN Office on Drugs and Crime) a Press Releases",
      "endpoint": "https://www.unodc.org/unodc/en/press/releases/latest.html",
      "finalUrl": "",
      "category": "not-found-404",
      "statusKind": "",
      "message": "HTTP 404",
      "status": 404,
      "rankScore": 5,
      "suggestedAction": "move source to quarantine and replace endpoint with current live URL",
      "replacementCandidate": "",
      "sourceKind": "html",
      "sourceLane": "context",
      "sourceRegion": "",
      "isMachineReadable": false
    },
    {
      "id": "westminster-city-council-news",
      "provider": "Westminster City Council a News",
      "endpoint": "https://www.westminster.gov.uk/news/rss",
      "finalUrl": "",
      "category": "not-found-404",
      "statusKind": "",
      "message": "HTTP 404",
      "status": 404,
      "rankScore": 5,
      "suggestedAction": "move source to quarantine and replace endpoint with current live URL",
      "replacementCandidate": "",
      "sourceKind": "rss",
      "sourceLane": "context",
      "sourceRegion": "",
      "isMachineReadable": true
    },
    {
      "id": "belgian-federal-police-news",
      "provider": "Belgian Federal Police - News",
      "endpoint": "https://www.politie.be/5998/en/news",
      "finalUrl": "https://www.police.be/5998/en/news",
      "category": "moved-temporarily",
      "statusKind": "",
      "message": "HTTP 404",
      "status": 404,
      "rankScore": 4,
      "suggestedAction": "update source endpoint to redirected final URL",
      "replacementCandidate": "https://www.police.be/5998/en/news",
      "sourceKind": "html",
      "sourceLane": "incidents",
      "sourceRegion": "",
      "isMachineReadable": false
    },
    {
      "id": "german-interior-ministry-press",
      "provider": "German Federal Ministry of the Interior - Press",
      "endpoint": "https://www.bmi.bund.de/EN/press/press-releases/press-releases-node.html",
      "finalUrl": "https://www.bmi.bund.de/cookie-check-d973?l=%2FEN%2. Fpress%2. Fpress%2. Dreleases%2. Fpress%2. Dreleases%2. Dnode%2. Ehtml&v=61405663&m=572902497&h=AWmEW37zQLu5iMHtf%2BC466wKF1dc. Aj4HYQ709Q5. QiXE",
      "category": "moved-temporarily",
      "statusKind": "",
      "message": "HTTP 400",
      "status": 400,
      "rankScore": 4,
      "suggestedAction": "update source endpoint to redirected final URL",
      "replacementCandidate": "https://www.bmi.bund.de/cookie-check-d973?l=%2FEN%2. Fpress%2. Fpress%2. Dreleases%2. Fpress%2. Dreleases%2. Dnode%2. Ehtml&v=61405663&m=572902497&h=AWmEW37zQLu5iMHtf%2BC466wKF1dc. Aj4HYQ709Q5. QiXE",
      "sourceKind": "html",
      "sourceLane": "context",
      "sourceRegion": "",
      "isMachineReadable": false
    },
    {
      "id": "guardia-civil-news",
      "provider": "Guardia Civil - News",
      "endpoint": "https://www.guardiacivil.es/es/prensa/noticias/",
      "finalUrl": "https://web.guardiacivil.es/es/prensa/noticias/",
      "category": "moved-temporarily",
      "statusKind": "",
      "message": "HTTP 404",
      "status": 404,
      "rankScore": 4,
      "suggestedAction": "update source endpoint to redirected final URL",
      "replacementCandidate": "https://web.guardiacivil.es/es/prensa/noticias/",
      "sourceKind": "html",
      "sourceLane": "incidents",
      "sourceRegion": "",
      "isMachineReadable": false
    }
  ]
}
